djangocms_code_prettify/__init__.py
djangocms_code_prettify/apps.py
djangocms_code_prettify/cms_plugins.py
djangocms_code_prettify/consts.py
djangocms_code_prettify/forms.py
djangocms_code_prettify/models.py
djangocms_code_prettify/tests.py
djangocms_code_prettify/migrations/0001_initial.py
djangocms_code_prettify/migrations/0002_codeprettify_start_linenum.py
djangocms_code_prettify/migrations/0003_auto_20190523_1318.py
djangocms_code_prettify/migrations/0004_codeprettify_show_all_linenums.py
djangocms_code_prettify/migrations/0005_codeprettify_autorun.py
djangocms_code_prettify/migrations/__init__.py
djangocms_code_prettify/templates/djangocms_code_prettify/code-prettify.html
djangocms_code_prettify-1.1.0.dist-info/LICENSE
djangocms_code_prettify-1.1.0.dist-info/METADATA
djangocms_code_prettify-1.1.0.dist-info/WHEEL
djangocms_code_prettify-1.1.0.dist-info/top_level.txt
djangocms_code_prettify-1.1.0.dist-info/RECORD
